mec_vibrations_calcs/__init__.py
mec_vibrations_calcs/n_dof_calc.py
mec_vibrations_calcs/one_dof_calc.py
mec_vibrations_calcs-0.1.2.dist-info/METADATA
mec_vibrations_calcs-0.1.2.dist-info/WHEEL
mec_vibrations_calcs-0.1.2.dist-info/licenses/LICENSE
mec_vibrations_calcs-0.1.2.dist-info/RECORD
