Metadata-Version: 2.4
Name: mec_vibrations_calcs
Version: 0.1.2
Summary: Vibration Analysis Tools
Project-URL: Homepage, https://github.com/Igor-Portifolio/mec-vibrations-calcs
Project-URL: Repository, https://github.com/Igor-Portifolio/mec-vibrations-calcs
Author-email: Igor Michalawiski Machado <immachad752@gmail.com>
License: MIT
License-File: LICENSE
Requires-Python: >=3.8
Requires-Dist: matplotlib>=3.5
Requires-Dist: numpy>=1.20
